AudioToText/AudioTextConverter.py
AudioToText/__init__.py
AudioToText-0.0.2.dist-info/LICENSE.txt
AudioToText-0.0.2.dist-info/METADATA
AudioToText-0.0.2.dist-info/WHEEL
AudioToText-0.0.2.dist-info/top_level.txt
AudioToText-0.0.2.dist-info/RECORD
