Metadata-Version: 2.1
Name: AudioToText
Version: 0.0.2
Summary: A small example package
Home-page: https://github.com/pypa/sampleproject
Author: ETM Automation pvt.ltd.
Author-email: author@example.com
License: UNKNOWN
Platform: UNKNOWN
Classifier: Programming Language :: Python :: 3
Classifier: License :: OSI Approved :: MIT License
Classifier: Operating System :: OS Independent
Requires-Python: >=3.6
Requires-Dist: pydub
Requires-Dist: SpeechRecognition
